{
  "いとくずを初めて入手したとき": "首次获得线头时",
  "かみのゴミを入手する": "获得废纸",
  "ぐにゃぐにゃねんどを入手した際に入手": "获得软黏土时取得",
  "ごつごつやまの街環境レベル5でショップ解放": "崎岖山环境等级 5 解锁商店",
  "せっかいせきを入手": "获得石灰石",
  "ちいさなおとしもの初回鑑定時": "首次鉴定小型遗落物时",
  "つたひも入手時に解放": "获得藤绳时解锁",
  "ひかるキノコを入手": "获得发光蘑菇",
  "ふしぎなげん入手時にひらめく": "获得神秘琴弦时领悟",
  "まっさらな街の北部で拾う": "在崭新小镇北部捡取",
  "まっさらな街の南部で拾う": "在崭新小镇南部捡取",
  "まっさらな街の東部で拾う": "在崭新小镇东部捡取",
  "まっさらな街環境レベル6でショップ解放": "崭新小镇环境等级 6 解锁商店",
  "まっさらな街環境レベル7でショップ解放": "崭新小镇环境等级 7 解锁商店",
  "まっさらな街環境レベル8でショップ解放": "崭新小镇环境等级 8 解锁商店",
  "ようこうろでてつののべぼうを作成": "在熔炉制作铁棒",
  "キラキラうきしまの街で入手": "在闪亮浮岛取得",
  "コンクリートを入手するとひらめく": "获得混凝土时领悟",
  "ゴツゴツやまの街のストーリーで入手": "在崎岖山剧情中取得",
  "ゴツゴツやまの街のストーリークリア後": "完成崎岖山剧情后",
  "ゴツゴツやまの街のストーリー中に入手": "在崎岖山剧情中取得",
  "ゴツゴツやまの街環境レベル2でショップ解放": "崎岖山环境等级 2 解锁商店",
  "ショップで400コインで購入(日替わり)": "在商店以 400 金币购买（每日更换）",
  "ショップで「うきしまのいえづくりレシピセット」を購入": "在商店购买「浮岛房屋建造配方套组」",
  "ショップで「うきしまのいえづくりレシピセット」を購入(キラキラうきしまの街Lv3)": "在商店购买「浮岛房屋建造配方套组」（闪亮浮岛 Lv. 3）",
  "ショップで「こうやのいえづくり」を購入(パサパサこうやLv3)": "在商店购买「荒野房屋建造」（干枯荒野 Lv. 3）",
  "ショップで「こうやのいえづくりレシピセット」を購入(パサパサこうやLv3)": "在商店购买「荒野房屋建造配方套组」（干枯荒野 Lv. 3）",
  "ショップで「ごうかなはしらレシピセット」を購入(日替わり)": "在商店购买「豪华柱子配方套组」（每日更换）",
  "ショップで「やねがわらレシピセット」を購入": "在商店购买「屋瓦配方套组」",
  "ショップで「やねがわらレシピセット」を購入(パサパサこうやの街Lv5)": "在商店购买「屋瓦配方套组」（干枯荒野 Lv. 5）",
  "ショップで「やまのいえづくりレシピセット」を購入": "在商店购买「山地房屋建造配方套组」",
  "ショップで「コンクリのふちのレシピセット」を購入": "在商店购买「混凝土边框配方套组」",
  "ショップで「木のけんざいレシピセット」を購入(パサパサこうやLv3)": "在商店购买「木制建材配方套组」（干枯荒野 Lv. 3）",
  "ショップで「木のふちのレシピセット」を購入": "在商店购买「木制边框配方套组」",
  "ショップでレシピを購入(日替わり)": "在商店购买配方（每日更换）",
  "ショップで購入(まっさらな街Lv10)": "在商店购买（崭新小镇 Lv. 10）",
  "ショップで購入(まっさらな街Lv2)": "在商店购买（崭新小镇 Lv. 2）",
  "ショップで購入(まっさらな街Lv3)": "在商店购买（崭新小镇 Lv. 3）",
  "ショップで購入(まっさらな街Lv4)": "在商店购买（崭新小镇 Lv. 4）",
  "ショップで購入(まっさらな街Lv5)": "在商店购买（崭新小镇 Lv. 5）",
  "ショップで購入(まっさらな街Lv8)": "在商店购买（崭新小镇 Lv. 8）",
  "ショップで購入(まっさらな街Lv9)": "在商店购买（崭新小镇 Lv. 9）",
  "ショップで購入(キラキラうきしまの街Lv10)": "在商店购买（闪亮浮岛 Lv. 10）",
  "ショップで購入(キラキラうきしまの街Lv2)": "在商店购买（闪亮浮岛 Lv. 2）",
  "ショップで購入(キラキラうきしまの街Lv3)": "在商店购买（闪亮浮岛 Lv. 3）",
  "ショップで購入(キラキラうきしまの街Lv4)": "在商店购买（闪亮浮岛 Lv. 4）",
  "ショップで購入(キラキラうきしまの街Lv5)": "在商店购买（闪亮浮岛 Lv. 5）",
  "ショップで購入(キラキラうきしまの街Lv6)": "在商店购买（闪亮浮岛 Lv. 6）",
  "ショップで購入(キラキラうきしまの街Lv7)": "在商店购买（闪亮浮岛 Lv. 7）",
  "ショップで購入(キラキラうきしまの街Lv8)": "在商店购买（闪亮浮岛 Lv. 8）",
  "ショップで購入(キラキラうきしまの街Lv9)": "在商店购买（闪亮浮岛 Lv. 9）",
  "ショップで購入(ゴツゴツやまの街Lv10)": "在商店购买（崎岖山 Lv. 10）",
  "ショップで購入(ゴツゴツやまの街Lv2)": "在商店购买（崎岖山 Lv. 2）",
  "ショップで購入(ゴツゴツやまの街Lv3)": "在商店购买（崎岖山 Lv. 3）",
  "ショップで購入(ゴツゴツやまの街Lv4)": "在商店购买（崎岖山 Lv. 4）",
  "ショップで購入(ゴツゴツやまの街Lv5)": "在商店购买（崎岖山 Lv. 5）",
  "ショップで購入(ゴツゴツやまの街Lv6)": "在商店购买（崎岖山 Lv. 6）",
  "ショップで購入(ゴツゴツやまの街Lv7)": "在商店购买（崎岖山 Lv. 7）",
  "ショップで購入(ゴツゴツやまの街Lv8)": "在商店购买（崎岖山 Lv. 8）",
  "ショップで購入(ゴツゴツやまの街Lv9)": "在商店购买（崎岖山 Lv. 9）",
  "ショップで購入(ドンヨリうみべの街Lv10)": "在商店购买（阴沉海滨 Lv. 10）",
  "ショップで購入(ドンヨリうみべの街Lv2)": "在商店购买（阴沉海滨 Lv. 2）",
  "ショップで購入(ドンヨリうみべの街Lv3)": "在商店购买（阴沉海滨 Lv. 3）",
  "ショップで購入(ドンヨリうみべの街Lv4)": "在商店购买（阴沉海滨 Lv. 4）",
  "ショップで購入(ドンヨリうみべの街Lv5)": "在商店购买（阴沉海滨 Lv. 5）",
  "ショップで購入(ドンヨリうみべの街Lv6)": "在商店购买（阴沉海滨 Lv. 6）",
  "ショップで購入(ドンヨリうみべの街Lv7)": "在商店购买（阴沉海滨 Lv. 7）",
  "ショップで購入(ドンヨリうみべの街Lv8)": "在商店购买（阴沉海滨 Lv. 8）",
  "ショップで購入(ドンヨリうみべの街Lv9)": "在商店购买（阴沉海滨 Lv. 9）",
  "ショップで購入(パサパサこうやの街Lv10)": "在商店购买（干枯荒野 Lv. 10）",
  "ショップで購入(パサパサこうやの街Lv2)": "在商店购买（干枯荒野 Lv. 2）",
  "ショップで購入(パサパサこうやの街Lv3)": "在商店购买（干枯荒野 Lv. 3）",
  "ショップで購入(パサパサこうやの街Lv4)": "在商店购买（干枯荒野 Lv. 4）",
  "ショップで購入(パサパサこうやの街Lv5)": "在商店购买（干枯荒野 Lv. 5）",
  "ショップで購入(パサパサこうやの街Lv6)": "在商店购买（干枯荒野 Lv. 6）",
  "ショップで購入(パサパサこうやの街Lv7)": "在商店购买（干枯荒野 Lv. 7）",
  "ショップで購入(パサパサこうやの街Lv8)": "在商店购买（干枯荒野 Lv. 8）",
  "ショップで購入(パサパサこうやの街Lv9)": "在商店购买（干枯荒野 Lv. 9）",
  "ショップで購入(日替わり)": "在商店购买（每日更换）",
  "ショップで購入(要：ドンヨリうみべの街のストーリー進行)": "在商店购买（需要：阴沉海滨剧情进度）",
  "ショップで購入(要：ピンプクのおねがいごとを進める)": "在商店购买（需要：推进小福蛋的请求）",
  "ショップで購入(解放条件調査中)": "在商店购买（解锁条件调查中）",
  "ストーリーではたを自宅に設置後に解放": "剧情中在自宅设置旗帜后解锁",
  "ストーリーでクラフト台解放時に入手": "剧情中解锁工作台时取得",
  "ストーリーでフシギダネのおねがい「ベッドを使ってもらおう」で入手": "剧情中完成妙蛙种子的请求「让人使用床铺吧」时取得",
  "ストーリーでヤドンと会話したときにもらう": "剧情中与呆呆兽对话时获得",
  "ドンヨリうみべの街で入手": "在阴沉海滨取得",
  "ドンヨリうみべの街で拾う": "在阴沉海滨捡取",
  "ドンヨリうみべの街のストーリー中に入手": "在阴沉海滨剧情中取得",
  "ニョロボンのおねがいごとを2回クリアで入手": "完成蚊香泳士的请求 2 次后取得",
  "パサパサこうやの街で入手": "在干枯荒野取得",
  "ファイヤー、サンダー、フリーザーを友達にすると解放": "与火焰鸟、闪电鸟、急冻鸟成为朋友后解锁",
  "ポケモン図鑑120匹登録時の報酬": "宝可梦图鉴登录 120 只时的奖励",
  "ポケモン図鑑130匹登録時の報酬": "宝可梦图鉴登录 130 只时的奖励",
  "ポケモン図鑑150匹登録時の報酬": "宝可梦图鉴登录 150 只时的奖励",
  "ポケモン図鑑200匹登録時の報酬": "宝可梦图鉴登录 200 只时的奖励",
  "ポケモン図鑑220匹登録時の報酬": "宝可梦图鉴登录 220 只时的奖励",
  "ポケモン図鑑30匹登録時の報酬": "宝可梦图鉴登录 30 只时的奖励",
  "ポケモン図鑑65匹登録時の報酬": "宝可梦图鉴登录 65 只时的奖励",
  "ポケモン図鑑70匹登録時の報酬": "宝可梦图鉴登录 70 只时的奖励",
  "ポケモン図鑑75匹登録時の報酬": "宝可梦图鉴登录 75 只时的奖励",
  "ポケモン図鑑7匹登録時の報酬": "宝可梦图鉴登录 7 只时的奖励",
  "ポケモン図鑑90匹登録時の報酬": "宝可梦图鉴登录 90 只时的奖励",
  "ヨロイのはへん入手時にひらめく": "获得铠甲碎片时领悟",
  "ライコウ、エンテイ、スイクンを友達にすると解放": "与雷公、炎帝、水君成为朋友后解锁",
  "ローブシンに話しかけて入手": "与修建老匠对话取得",
  "水のキラキラからランダムで入手": "从水中闪光随机取得",
  "水の中のキラキラから入手": "从水中闪光取得",
  "水面のキラキラから入手": "从水面闪光取得"
}
