{
  "id": 93,
  "slug": "gastly",
  "name": "Gastly",
  "types": [
    "ghost",
    "poison"
  ],
  "image": "https://assets.pokopiaguide.com/pokemon/gastly.png",
  "pokopia": {
    "specialties": [
      "gather",
      "trade"
    ],
    "favorites": [],
    "timeOfDay": [
      "night"
    ],
    "weather": [
      "sunny",
      "cloudy",
      "rainy"
    ],
    "obtainMethod": "habitat",
    "evolvesFrom": null,
    "evolvesTo": [
      "haunter"
    ],
    "habitats": [
      {
        "id": 89,
        "name": "Spooky study",
        "rarity": "common"
      }
    ]
  }
}
