{
  "id": 212,
  "slug": "politoed",
  "name": "蚊香蛙皇",
  "types": [
    "water"
  ],
  "image": "https://assets.pokopiaguide.com/pokemon/politoed.png",
  "pokopia": {
    "specialties": [
      "water",
      "hype"
    ],
    "timeOfDay": [
      "dawn",
      "day",
      "dusk",
      "night"
    ],
    "weather": [
      "sunny",
      "cloudy",
      "rainy"
    ],
    "obtainMethod": "habitat",
    "evolvesFrom": "poliwhirl",
    "evolvesTo": null,
    "habitats": [
      {
        "id": 107,
        "name": "花田樹樁舞台",
        "rarity": "rare"
      },
      {
        "id": 114,
        "name": "ととのう温泉",
        "rarity": "common"
      }
    ]
  }
}
