{
  "id": 149,
  "slug": "clefairy",
  "name": "ピッピ",
  "types": [
    "fairy"
  ],
  "stats": {
    "hp": 70,
    "attack": 45,
    "defense": 48,
    "spAtk": 60,
    "spDef": 65,
    "speed": 35
  },
  "abilities": [
    "メロメロボディ",
    "マジックガード",
    "フレンドガード"
  ],
  "description": "愛くるしい　しぐさと　鳴き声で かわいいと　大人気の　ポケモン。 だが　めったに　見つからない。",
  "image": "https://assets.pokopiaguide.com/pokemon/clefairy.png",
  "pokopia": {
    "specialties": [
      "hype"
    ],
    "timeOfDay": [
      "night"
    ],
    "weather": [
      "sunny",
      "cloudy",
      "rainy"
    ],
    "obtainMethod": "habitat",
    "evolvesFrom": "dragonair",
    "evolvesTo": null,
    "habitats": [
      {
        "id": 131,
        "name": "銅像の観光スポット",
        "rarity": "common"
      }
    ]
  }
}
