{
  "id": 823,
  "slug": "corviknight",
  "name": "アーマーガア",
  "types": [
    "flying",
    "steel"
  ],
  "stats": {
    "hp": 98,
    "attack": 87,
    "defense": 105,
    "spAtk": 53,
    "spDef": 85,
    "speed": 67
  },
  "abilities": [
    "pressure",
    "unnerve",
    "mirror-armor"
  ],
  "description": "飛行能力に　優れていて とても　賢いため　ガラル地方で 空の　タクシーとして　活躍。",
  "image": "https://assets.pokopiaguide.com/pokemon/corviknight.png",
  "pokopia": {
    "specialties": [],
    "timeOfDay": null,
    "weather": null,
    "obtainMethod": "habitat",
    "evolvesFrom": "corvisquire",
    "evolvesTo": null,
    "habitats": []
  }
}
