{
  "id": 38,
  "slug": "koffing",
  "name": "ドガース",
  "types": [
    "poison"
  ],
  "image": "https://assets.pokopiaguide.com/pokemon/koffing.png",
  "pokopia": {
    "specialties": [
      "recycle"
    ],
    "favorites": [
      "garbage",
      "gatherings",
      "complicated stuff",
      "soft stuff",
      "wobbly stuff",
      "bitter flavors"
    ],
    "timeOfDay": [
      "dawn",
      "day",
      "dusk",
      "night"
    ],
    "weather": [
      "sunny",
      "cloudy",
      "rainy"
    ],
    "obtainMethod": "habitat",
    "evolvesFrom": null,
    "evolvesTo": [
      "weezing"
    ],
    "habitats": [
      {
        "id": 63,
        "name": "ゴミ集積所",
        "rarity": "common"
      }
    ]
  }
}
