{
  "id": 156,
  "slug": "machop",
  "name": "ワンリキー",
  "types": [
    "fighting"
  ],
  "image": "https://assets.pokopiaguide.com/pokemon/machop.png",
  "pokopia": {
    "specialties": [
      "build",
      "gather"
    ],
    "timeOfDay": [
      "dawn",
      "day",
      "dusk",
      "night"
    ],
    "weather": [
      "sunny",
      "cloudy",
      "rainy"
    ],
    "obtainMethod": "habitat",
    "evolvesFrom": "cyndaquil",
    "evolvesTo": null,
    "habitats": [
      {
        "id": 3,
        "name": "岩かげの草むら",
        "rarity": "common"
      }
    ]
  }
}
