{
  "id": 210,
  "slug": "poliwhirl",
  "name": "ニョロゾ",
  "types": [
    "water"
  ],
  "image": "https://assets.pokopiaguide.com/pokemon/poliwhirl.png",
  "pokopia": {
    "specialties": [
      "water"
    ],
    "favorites": [
      "lots of water",
      "cleanliness",
      "lots of nature",
      "exercise",
      "spinning stuff",
      "bitter flavors"
    ],
    "timeOfDay": [
      "dawn",
      "day",
      "dusk",
      "night"
    ],
    "weather": [
      "sunny",
      "cloudy",
      "rainy"
    ],
    "obtainMethod": "habitat",
    "evolvesFrom": "poliwag",
    "evolvesTo": [
      "poliwrath",
      "politoed"
    ],
    "habitats": [
      {
        "id": 144,
        "name": "うるおうフワフワな花畑",
        "rarity": "rare"
      }
    ]
  }
}
